{
  "longitudinal_controller": {
    "100": {
          "Kp": 0.9,
          "Kd": 0.2,
          "Ki": 0
    },
    "110": {
          "Kp": 0.5,
          "Kd": 0.2,
          "Ki": 0
    },
    "150": {
          "Kp": 0.3,
          "Kd": 0.2,
          "Ki": 0
        }
  },
  "latitudinal_controller": {
    "100": {
          "Kp": 0.03,
          "Kd": 0.05,
          "Ki": 0.1
    },
    "110": {
          "Kp": 0.45,
          "Kd": 0.3,
          "Ki": 0.03
    },
    "150": {
          "Kp": 0.4,
          "Kd": 0.2,
          "Ki": 0.01
        }
  }
}