{
  "longitudinal_controller": {
    "100": {
          "Kp": 0.9,
          "Kd": 0.2,
          "Ki": 0
    },
    "110": {
          "Kp": 0.5,
          "Kd": 0.2,
          "Ki": 0
    },
    "150": {
          "Kp": 0.2,
          "Kd": 0.2,
          "Ki": 0
        }
  },
  "latitudinal_controller": {
    "100": {
          "Kp": 0.05,
          "Kd": 0.01,
          "Ki": 0.1
    },
    "110": {
          "Kp": 0.5,
          "Kd": 0.05,
          "Ki": 0.03
    },
    "140": {
          "Kp": 0.2,
          "Kd": 0.15,
          "Ki": 0.01
        },
        "150": {
              "Kp": 0.5,
              "Kd": 0.18,
              "Ki": 0.01
            },
        "180": {
              "Kp": 0.8,
              "Kd": 0.2,
              "Ki": 0.01
            },
            "220": {
                  "Kp": 1,
                  "Kd": 0.5,
                  "Ki": 0.01
                }
  }
}